[
  {
    "start": 0.0,
    "end": 8.0,
    "text": "Thầy thân bá đang vịn thang chèo lên tường viện nhìn ra ngoài. Thầy ân oánh đến, ông vội vàng chèo xuống."
  },
  {
    "start": 8.0,
    "end": 16.0,
    "text": "Ơn oánh vội vàng đưa tay đỡ, cẩn thận. Đợi ông bước xuống đất, ân oánh vội vàng hỏi, bên ngoài xảy ra chuyện gì vậy."
  },
  {
    "start": 16.0,
    "end": 23.0,
    "text": "Thân bá nói, giới nghiêm. Ơn oánh hỏi, là binh lính của ai. Thân bá lắc đầu, lão nô cũng không biết."
  },
  {
    "start": 23.0,
    "end": 42.0,
    "text": "Thân bà muốn ngăn cản, Ấn Oánh nói, không tận mắt nhìn thấy, ta không yên tâm. Thân bà nghĩ lại, cũng có lý. Hơn nửa ông đã lớn tuổi, biết rõ tính tỉnh những người trẻ tuổi. Càng ngăn cản, bọn họ càng làm trái. Ông bèn đồng ý, đừng thò đầu ra ngoài."
  },
  {
    "start": 42.0,
    "end": 43.0,
    "text": "Thò đầu ra ngoài."
  },
  {
    "start": 43.0,
    "end": 46.44,
    "text": "Ân oánh gật đầu, sau đó sách váy trèo lên thang."
  },
  {
    "start": 46.44,
    "end": 49.12,
    "text": "Nàng cẩn thận từng ly từng tí thò đầu ra ngoài."
  },
  {
    "start": 49.12,
    "end": 54.0,
    "text": "Nhìn về phía đầu đường có thể thấy rất nhiều ngọn đuốc, bóng người lay động, cửa bị chặn,"
  },
  {
    "start": 54.0,
    "end": 56.0,
    "text": "hiển nhiên là để ngăn người dân đi lại."
  },
  {
    "start": 56.0,
    "end": 62.68,
    "text": "Nàng quan sát một lúc, sau đó trèo xuống, không nhìn rõ là quân của ai, nhưng chắc chắn không phải là cấm vệ quân."
  },
  {
    "start": 62.68,
    "end": 67.0,
    "text": "Nàng trèo xuống, sau đó bảo một gã sai vặt trèo lên quan sát."
  },
  {
    "start": 67.0,
    "end": 78.48,
    "text": "Gã sai vặt kia cao lớn, cổ lại dài, vừa treo lên đã thò cổ ra ngoài rò xét. Bỗng nhiên dưới tường có người quát lớn, nhìn cái gì mà nhìn, còn nhìn nữa móc mắt người bây giờ."
  },
  {
    "start": 78.48,
    "end": 84.52,
    "text": "Hóa ra là có người đang tiểu tiện dưới tường, ngẩn đầu lên nhìn, thấy có một cái đầu thò ra từ trên tường."
  },
  {
    "start": 84.52,
    "end": 91.2,
    "text": "Ấn hoánh vội vàng tiến lên phía trước, đưa tay giữ thang, thấp giọng nói, ngươi hỏi hắn xem, là quân của ai."
  },
  {
    "start": 91.2,
    "end": 96.48,
    "text": "Gã sai vặt ở trên cao lên tiếng hỏi, vị quân gia này, xin hỏi ngài là người của ai."
  },
  {
    "start": 96.48,
    "end": 105.22,
    "text": "Người nọ đáp, quân doanh Kinh Thành, quân lương ra ở Kinh Kỳ, thân quân của Hoàng Thượng, mau rụt vào, đang giới nghiêm, không được ra ngoài."
  },
  {
    "start": 105.22,
    "end": 114.68,
    "text": "Ấn Oánh nói, người nói xem, hóa ra là quân doanh Kinh Thành, dọa chết ta rồi. Nếu sớm biết là quân doanh Kinh Thành, ta đã không sợ hãi như vậy rồi."
  },
  {
    "start": 114.68,
    "end": 120.68,
    "text": "Ba đại doanh của quân doanh Kinh Thành đều là thân quân của Hoàng Thượng, đều xuất thân từ những gia đình lương thiện ở Kinh Thành."
  },
  {
    "start": 120.68,
    "end": 129.04,
    "text": "Trách nhiệm của bọn họ là bảo vệ Kinh Thành, còn cấm vệ quân chính là vũ lâm vệ, lòng tường vệ, phụ trách bảo vệ Hoàng Cung và nghi trượng của Hoàng Thượng."
  },
  {
    "start": 129.04,
    "end": 135.68,
    "text": "Những thứ này, vốn không nằm trong kiến thức của ân oánh ở kiếp trước, cũng không phải là chuyện nàng cần phải biết ở kiếp này."
  },
  {
    "start": 135.68,
    "end": 141.24,
    "text": "Trước đó nàng vốn chẳng bận tâm đến những chuyện này. Nhưng về sau lại động tâm tư kia thì sao?"
  },
  {
    "start": 141.24,
    "end": 144.7,
    "text": "Đã động tâm tư, tự nhiên chẳng cần phải ra ngoài do hỏi."
  },
  {
    "start": 144.7,
    "end": 147.2,
    "text": "Trong nhà có sẵn một kho chi thức là thẩm đề,"
  },
  {
    "start": 147.2,
    "end": 151.0,
    "text": "chỉ cần vời như tò mò về kinh thành rồi từ từ hỏi hán hắn là được."
  },
  {
    "start": 151.0,
    "end": 153.0,
    "text": "Những điều này nào phải cơ mật gì,"
  },
  {
    "start": 153.0,
    "end": 156.8,
    "text": "với thẩm đề mà nói đều là thưởng thức cơ bản mà quan viên nào cũng phải biết,"
  },
  {
    "start": 156.8,
    "end": 159.0,
    "text": "ẩn oánh hỏi, hắn liền nói."
  },
  {
    "start": 159.0,
    "end": 162.0,
    "text": "Nàng luôn nghe say xưa, ánh mắt sáng rực."
  },
  {
    "start": 162.0,
    "end": 164.3,
    "text": "Thẩm đề cũng nói rất hào hứng."
  },
  {
    "start": 164.3,
    "end": 166.1,
    "text": "Các tỷ nữ ở ngoài phòng,"
  },
  {
    "start": 166.1,
    "end": 170.8,
    "text": "nói, xem kìa, hàn lâm đại nhân và thiếu phu nhân ngày nào cũng có chuyện để nói."
  },
  {
    "start": 170.8,
    "end": 173.92,
    "text": "Một người nói hay, một người nhớ nhanh lại chăm chú."
  },
  {
    "start": 173.92,
    "end": 180.48,
    "text": "Giờ đây những thông tin mà ơn oánh thích lũy được về Kinh Thành chẳng kém gì thẩm phu nhân đã sống ở Kinh Thành hơn 20 năm."
  },
  {
    "start": 180.48,
    "end": 187.72,
    "text": "Thậm chí nàng còn nắm được rất nhiều thông tin mà thẩm phu nhân cho là không cần thiết phải quan tâm, chẳng liên quan gì đến các phu nhân trong nhà."
  },
  {
    "start": 187.72,
    "end": 193.88,
    "text": "Gia Nô vốn là người hầu hạ ở cửa, mà người hầu hạ ở cửa phần lớn đều là người lanh lợi, ăn nói khéo léo."
  },
  {
    "start": 193.88,
    "end": 198.48,
    "text": "Hắn vội vàng nói, thi ra là quân doanh Kinh Thành, gù chết, gù chết."
  },
  {
    "start": 198.48,
    "end": 205.48,
    "text": "Nếu sớm biết là quân doanh kinh thành thì đã chẳng sợ hãi, đều là con em lương ra ở kinh kỳ chúng ta, là quân đội của thiên tử.\""
  },
  {
    "start": 205.48,
    "end": 207.48,
    "text": "Lời này là đang tầng bốc."
  },
  {
    "start": 207.48,
    "end": 215.48,
    "text": "Đen kia sửa sang lại thắt lưng, hư một tiếng, nói, bảo ngươi trong phủ các người, khóa chặt cửa, không được chạy loạn ra ngoài."
  },
  {
    "start": 215.48,
    "end": 217.48,
    "text": "Jano vội vàng đáp, vâng, vâng."
  },
  {
    "start": 217.48,
    "end": 221.48,
    "text": "Ấn oánh nói, người hỏi hắn có muốn uống nước nóng không?"
  },
  {
    "start": 221.48,
    "end": 223.48,
    "text": "Jano lại hô lớn, quân ra."
  },
  {
    "start": 223.48,
    "end": 227.48,
    "text": "Tên kia đã cất bước đi về phía đầu phố, lại bị gọi giật lại."
  },
  {
    "start": 227.48,
    "end": 231.48,
    "text": "Bị gọi lại, hắn ta không khỏi mất kiên nhẫn, quay đầu định mắng."
  },
  {
    "start": 231.48,
    "end": 238.48,
    "text": "Bây giờ mới là tháng 2, tuy thời tiết đã bắt đầu ấm lên, nhưng lúc này là ban đêm, chân lạnh cóng đến đau."
  },
  {
    "start": 238.48,
    "end": 242.48,
    "text": "Sao có thể giữ được bình tĩnh? Và lại người trên tường lại hỏi,"
  },
  {
    "start": 242.48,
    "end": 246.48,
    "text": "có muốn uống nước nóng không, đêm hôm khuya khuất thế này, lạnh làm đấy?"
  },
  {
    "start": 246.48,
    "end": 251.48,
    "text": "Muốn không, một câu chửi tục vốn sắp bật ra khỏi miệng bỗng chốc được hắn ta nuốt xuống,"
  },
  {
    "start": 251.48,
    "end": 255.28,
    "text": "À, nước nóng à, được đấy, tiện thi cho ta một bình.\""
  },
  {
    "start": 255.28,
    "end": 258.08,
    "text": "Giano nói, quân ra chờ một lát."
  },
  {
    "start": 258.08,
    "end": 260.32,
    "text": "Nói rồi hắn ta trẻo xuống."
  },
  {
    "start": 260.32,
    "end": 263.08,
    "text": "Thân bá lập tức sai người đi lấy nước nóng."
  },
  {
    "start": 263.08,
    "end": 265.56,
    "text": "Ân oánh nói, lấy nhiều một chút."
  },
  {
    "start": 265.56,
    "end": 273.32,
    "text": "Nước nóng đã chuẩn bị sẵn, bởi vì tối nay vốn đã bố trí rất nhiều Giano canh cửa, cơm nước, nước nóng đều chuẩn bị đầy đủ."
  },
  {
    "start": 273.32,
    "end": 276.32,
    "text": "Lập tức múc đầy một thùng gỗ, đậy nắp lại."
  },
  {
    "start": 276.32,
    "end": 279.32,
    "text": "Trên nắp có chốt, cài lại thì sẽ không mở ra."
  },
  {
    "start": 279.32,
    "end": 284.32,
    "text": "Quai thùng buộc chặt dây thường, sau đó bắc thang, sai Giano khỏe mạnh khiêng lên tường."
  },
  {
    "start": 284.32,
    "end": 294.32,
    "text": "Tên Giano lạnh lợi lúc trước cũng trèo lên, nói vọng xuống, quân gia, trong nhà có quy củ, ban đêm không được mở cửa, để tiểu nhân dùng dây thường treo xuống cho quân gia."
  },
  {
    "start": 294.32,
    "end": 300.32,
    "text": "Quân gia lui ra sau một chút, đừng để nước nóng văng chúng. Tên kia đáp, được rồi."
  },
  {
    "start": 300.32,
    "end": 308.32,
    "text": "Sau đó hắn ta thấy trên tường có người dùng dây thường treo xuống một thùng nước lớn, ôi, thùng nước to thật, quả là một gia đình hào phóng."
  },
  {
    "start": 308.32,
    "end": 312.04,
    "text": "Đa tạ, tên kia cởi dây thường, xách thùng nước nóng rời đi."
  },
  {
    "start": 312.04,
    "end": 316.56,
    "text": "Từ xa có thể nghe thấy tiếng hắn ta vọng lại trên đường, có nước nóng rồi."
  },
  {
    "start": 316.56,
    "end": 319.72,
    "text": "Phía xa xa chuyển đến tiếng đáp lời của rất nhiều người,"
  },
  {
    "start": 319.72,
    "end": 325.36,
    "text": "nước nóng, ở đâu ra thế, tốt đấy, mau đưa cho ta một ngụ, lạnh chết ông mày rồi."
  },
  {
    "start": 325.36,
    "end": 330.44,
    "text": "Mũ giáp tháo ra lật ngược lại chính là bát cơm, đương nhiên cũng có thể dùng để uống nước."
  },
  {
    "start": 330.44,
    "end": 333.56,
    "text": "Nghe nói có nước nóng, mọi người đều chạy tới."
  },
  {
    "start": 333.56,
    "end": 338.16,
    "text": "Lạnh quá, ai mà chẳng muốn uống một ngụ nước nóng, lấy đâu ra thế."
  },
  {
    "start": 338.16,
    "end": 349.28,
    "text": "Nhà kia cho đấy. Từ ngã rẽ này đi vào, đến ngã rẽ tiếp theo, thực ra chỉ có một nhà. Cửa có đặt đá kê chân cột hình dương với hình con sư tử, là nhà quan văn."
  },
  {
    "start": 349.28,
    "end": 356.28,
    "text": "Chia nước nóng xong, anh em ai nấy đều được uống vài ngụ, trong bụng ấm lên không ít, tên ban nãy sách thủng đi trả."
  },
  {
    "start": 356.28,
    "end": 363.6,
    "text": "Giây thừng vẫn còn đó, buộc vào là được, được rồi, kéo lên đi. Hắn ta nói, Đa Tạ, huynh đệ."
  },
  {
    "start": 363.6,
    "end": 368.84,
    "text": "Trong lúc chờ đợi, ân oánh đã bản bạc với Gia Nô, hắn ta đã biết nên nói gì."
  },
  {
    "start": 368.84,
    "end": 376.16,
    "text": "Gia chủ nhà ta hỏi, sáng mai các vị còn ở đó không? Nếu còn, nhà ta sẽ nấu một nồi canh nóng cho các vị."
  },
  {
    "start": 376.16,
    "end": 384.04,
    "text": "Các huynh đệ quân doanh Kinh Thành vất vả rồi. Tên kia mím môi, trong đêm đông lạnh giá này thật sự không thể nào cử tuyệt hai chữ canh nóng kia."
  },
  {
    "start": 384.04,
    "end": 385.76,
    "text": "Phủ Thượng là nhà ai thế?"
  },
  {
    "start": 385.76,
    "end": 392.56,
    "text": "Chờ hắn ta hỏi câu này, Gia Nô nói, Gia chủ nhà ta là thẩm đại nhân, nhậm chức hữu thông chính của thông chính ti."
  },
  {
    "start": 392.56,
    "end": 398.04,
    "text": "Thiếu ra nhà ta đang nhậm chức hắn Lâm Thị Giảng ở hắn Lâm Viện, là thám hoa lang của kỳ thi năm nay."
  },
  {
    "start": 398.04,
    "end": 405.08,
    "text": "Ô, quan viên ở Kinh Thành nhiều như Lông Châu, tả thông chính hữu thông chính gì đó, hắn ta nào biết ai với ai."
  },
  {
    "start": 405.08,
    "end": 411.6,
    "text": "Nhưng tiểu thẩm thám hoa thì hắn ta biết, thi ra là nhà của tiểu thẩm thám hoa à, con trai còn nổi tiếng hơn cha."
  },
  {
    "start": 411.6,
    "end": 425.4,
    "text": "Quân gia, gia chủ nhà ta và thiếu gia hôm nay đều chưa về. Tùy Tùng cũng chưa thấy ai về. Xin hỏi, sáng mai bọn họ có thể về được không? Nếu không thể, có thể để nhà ta đưa chút thức ăn nước uống cho bọn họ được không?\""
  },
  {
    "start": 425.4,
    "end": 432.0,
    "text": "Có qua có lại mới tội lòng nhau. Đên kia đáp, chuyện ngày mai còn chưa biết, tối nay không được ra ngoài."
  },
  {
    "start": 432.0,
    "end": 435.96,
    "text": "Gia ngoài là bị bắt, nếu dám chống cực, giết ngay tại chỗ."
  },
  {
    "start": 435.96,
    "end": 439.8,
    "text": "Lệnh từ cấp trên đấy, nghe rõ chưa, đừng có chạy loạn."
  },
  {
    "start": 439.8,
    "end": 442.88,
    "text": "Gia nô toát mổ hôi lạnh, vâng, vâng."
  },
  {
    "start": 442.88,
    "end": 448.28,
    "text": "Lại nói, gia chủ nhà ta nói, sáng mai sẽ sai người mang thêm hai thùng canh nóng nữa."
  },
  {
    "start": 448.28,
    "end": 452.48,
    "text": "Đền kia nói, vậy thì ngại quá, thay chúng ta đa tạ gia chủ."
  },
  {
    "start": 452.48,
    "end": 454.96,
    "text": "Hai bên bền hẹn giờ đến lấy canh."
  },
  {
    "start": 454.96,
    "end": 458.6,
    "text": "Giao cải và đậu hũ chiên, bắt đầu nấu từ bây giờ."
  },
  {
    "start": 458.6,
    "end": 465.6,
    "text": "Trong phủ, Ấn Oánh đã phân phó, dùng xương hầm canh lúc nãy, trước tiên không cần hầm canh, cứ hầm canh xương."
  },
  {
    "start": 465.6,
    "end": 469.36,
    "text": "Cho củ cải vào hầm, hầm càng lâu thì nước canh càng ngọt."
  },
  {
    "start": 469.36,
    "end": 476.56,
    "text": "Dùng luôn phòng bếp lớn của ngoại viện để nấu, không chỉ nấu cho quân doanh kinh thành bên ngoài, mà còn nấu cho các gia nô trực đêm."
  },
  {
    "start": 476.56,
    "end": 481.16,
    "text": "Ấn Oánh thương lượng với thân bá, chia gia nô trực đêm thành ba ca thay phiên nhau."
  },
  {
    "start": 481.16,
    "end": 488.36,
    "text": "Lại hỏi thân bá, ta nghe nói lão già muốn tích chữ lương thực trong nhà đủ dùng cho một năm, bây giờ đã tích chữ được bao nhiêu rồi?"
  },
  {
    "start": 488.36,
    "end": 496.36,
    "text": "Thân bá không ngờ chuyện này thẩm đề cũng nói cho Ấn Oánh biết, Hán tiếp xúc với Ấn Oánh không nhiều, đêm nay mới coi như là thật sự hiểu rõ nàng."
  },
  {
    "start": 496.36,
    "end": 499.36,
    "text": "Thật sự phải nhìn nàng với ánh mắt khắc xưa."
  },
  {
    "start": 499.36,
    "end": 504.36,
    "text": "Ban đầu Hán cứ tưởng nàng cũng giống như thẩm phu nhân, là một phu nhân quan viên đủ tiêu chuẩn."
  },
  {
    "start": 504.36,
    "end": 515.36,
    "text": "Không ngờ nàng lại là người như thế này, thật sự là Hán cũng kính đáp, sợ quá phô trương nên đều chuyển vào từ từ, số lương thực hiện tại đủ cho toàn bộ người trong phủ dùng trong 11 tháng."
  },
  {
    "start": 515.36,
    "end": 517.36,
    "text": "Ấn oánh thở phào nhẹ nhóm."
  },
  {
    "start": 517.36,
    "end": 523.36,
    "text": "Trước đây nàng sống trong thời bình, chưa từng trải qua nạn đói, nên không thể nào hiểu rõ được tầm quan trọng của lương thực."
  },
  {
    "start": 523.36,
    "end": 528.36,
    "text": "Bây giờ, nàng quản lý gia đình phải lo cho gần 100 người trong phủ ăn no mặc ấm."
  },
  {
    "start": 528.36,
    "end": 535.36,
    "text": "Trước kia sống trong thời bình thịnh thế, vật tư vô cùng phong phú, quốc gia luôn không ngừng nhấn mạnh vấn đề an ninh lương thực."
  },
  {
    "start": 535.36,
    "end": 540.36,
    "text": "Lúc đó 4 chữ an ninh lương thực quá xa vời với nàng, nhưng bây giờ thì nàng đã hiểu rõ."
  },
  {
    "start": 540.36,
    "end": 545.5,
    "text": "Lương thực đủ dùng cho 11 tháng, thật sự khiến cho người ta cảm thấy vô cùng an tâm."
  },
  {
    "start": 545.5,
    "end": 548.3,
    "text": "Lúc này vẫn là nửa đêm, lạnh buốt người."
  },
  {
    "start": 548.3,
    "end": 553.64,
    "text": "Thân bá nói, thiếu phu nhân mau về phòng nghỉ ngơi đi, nơi này cứ để lão nô trông là được."
  },
  {
    "start": 553.64,
    "end": 560.14,
    "text": "Ấn Oánh dặn dò, thân bá cũng nên nghỉ ngơi một chút, đừng thức khuya quá, cả phủ còn đang trông cậy vào ngươi đấy,"
  },
  {
    "start": 560.14,
    "end": 562.14,
    "text": "nói rồi nàng trở về nội viện."
  },
  {
    "start": 562.14,
    "end": 565.3,
    "text": "Gian chính trong sân của thẩm phu nhân vẫn còn sáng đèn."
  },
  {
    "start": 565.3,
    "end": 568.04,
    "text": "Thẩm phu nhân và tần mama đều đang đợi nàng."
  },
  {
    "start": 568.04,
    "end": 572.46,
    "text": "Thấy ơn oánh trở về, thẩm phu nhân liền hỏi, bên ngoài thế nào rồi?"
  },
  {
    "start": 572.46,
    "end": 577.54,
    "text": "Ơn oánh kể lại tình hình bên ngoài, nói, là quân doanh kinh thành, vậy thì tốt."
  },
  {
    "start": 577.54,
    "end": 586.9,
    "text": "Bởi vì đều là con em lương ra ở Kinh Kỳ được tuyển chọn vào quân doanh, đều là người ở đây, cho dù có xảy ra hỗn loạn, bọn họ cũng sẽ không tàn phá quê hương mình."
  },
  {
    "start": 586.9,
    "end": 591.86,
    "text": "Đến lúc này, ơn oánh bày kể chuyện ngoại viện tích chữ lương thực cho thẩm phu nhân nghe."
  },
  {
    "start": 591.86,
    "end": 595.9,
    "text": "Thẩm phu nhân nói, bọn họ lại âm thẩm chuẩn bị ký càng như thế."
  },
  {
    "start": 595.9,
    "end": 600.24,
    "text": "Nàng oan trách, những chuyện này cha chồng người chưa từng nói với ta một tiếng nào."
  },
  {
    "start": 600.24,
    "end": 603.92,
    "text": "Lương thực đều cất trong kho, người trong phủ nên biết đều biết."
  },
  {
    "start": 603.92,
    "end": 606.56,
    "text": "Thẩm phu nhân không biết cũng chẳng ảnh hưởng gì."
  },
  {
    "start": 606.56,
    "end": 609.8,
    "text": "Nhưng nếu bà biết, trong khoảng thời gian dài tích chữ lương thực,"
  },
  {
    "start": 609.8,
    "end": 615.26,
    "text": "thật sự không thể nào đảm bảo được bà có lỡ miệng nói cho vị phu nhân nào đó là bạn bè của mình hay không."
  },
  {
    "start": 615.26,
    "end": 617.76,
    "text": "Con người thật sự rất khó giữ bí mật."
  },
  {
    "start": 617.76,
    "end": 621.8,
    "text": "Giá lương thực tăng vọt, người quen biết biết nhà chúng ta có lương thực,"
  },
  {
    "start": 621.8,
    "end": 625.76,
    "text": "đến mượn, có cho mượn hay không, không thể để người ngoài biết được."
  },
  {
    "start": 625.76,
    "end": 635.34,
    "text": "Ấn Oanh nói, nếu không, nếu kinh thành thật sự đại loạn, giá lương thực tăng vọt, thương nhân ổ à tích chữ lương thực, một số nhà quen biết đến mượn lương thực thì sao?"
  },
  {
    "start": 635.34,
    "end": 642.26,
    "text": "Thẩm phu nhân nói, vậy, dù sao cũng phải cho bọn họ mượn một chút chứ. Mượn bao nhiêu? Mượn bao lâu?"
  },
  {
    "start": 642.26,
    "end": 650.7,
    "text": "Lỗi như nhà chúng ta hết lương thực, cả trăm người trong phủ không có gì ăn, thì nhà bọn họ có trả lại lương thực cho chúng ta không? Thẩm phu nhân im lặng."
  },
  {
    "start": 650.7,
    "end": 657.14,
    "text": "Bà làm chủ mẫu trong nhà đã hơn 20 năm, trong lòng bà biết rất rõ cả phủ này một ngày tiêu hao bao nhiêu lương thực."
  },
  {
    "start": 657.14,
    "end": 662.94,
    "text": "Cho mượn một ngày, hai ngày, mười ngày, vậy đến ngày thứ 11, có cho mượn tiếp hay không?"
  },
  {
    "start": 662.94,
    "end": 668.98,
    "text": "Nếu cho mượn, nhà mình sẽ không có lương thực, nếu không cho mượn, thì ân tình trước kia đều biến thành thù hận."
  },
  {
    "start": 668.98,
    "end": 673.82,
    "text": "Ấn Oánh ở nhà Trấn An thẩm phu nhân, còn thẩm Đại nhân thì đang hối hận không thôi."
  },
  {
    "start": 673.82,
    "end": 678.7,
    "text": "Mọi người nghe nói Cung thành bị phong tỏa, cấm ra vào, đều biết đã xảy ra chuyện."
  },
  {
    "start": 678.7,
    "end": 682.02,
    "text": "Thẩm Đại nhân càng biết rõ thẩm đề hôm nay đang ở trong cung."
  },
  {
    "start": 682.02,
    "end": 686.7,
    "text": "Ông ta đi theo mọi người đến quỳ trước cửa cung, yêu cầu người trong cung cho một câu trả lời."
  },
  {
    "start": 686.7,
    "end": 689.7,
    "text": "Lúc quần thần phẫn nộ, cửa cung mở ra."
  },
  {
    "start": 689.7,
    "end": 691.7,
    "text": "Mọi người đi vào trong."
  },
  {
    "start": 691.7,
    "end": 695.7,
    "text": "Thật ra với tính cách cầu ổn của Thẩm Đại nhân, ông ta đã do dự một lúc,"
  },
  {
    "start": 695.7,
    "end": 701.7,
    "text": "nhưng con trai đang ở trong cung, cuối cùng ông ta vẫn đi theo mọi người vào trong, sau đó bị vây chặt như bánh chưng."
  },
  {
    "start": 701.7,
    "end": 703.7,
    "text": "Toàn bộ đều bị giam lại."
  },
  {
    "start": 703.7,
    "end": 711.06,
    "text": "Các quan văn bị giam lại, bên ngoài có binh lính canh giữ, bọn họ chẳng thể làm gì, chỉ có thể đoán, rút cuộc là ai."
  },
  {
    "start": 711.06,
    "end": 714.42,
    "text": "Hoàng đế xảy ra chuyện, đây là điều ai cũng đoán được."
  },
  {
    "start": 714.42,
    "end": 718.98,
    "text": "Bây giờ chỉ là muốn biết, rút cuộc Cung Thành đã rơi vào tay vị Vương ra nào."
  },
  {
    "start": 718.98,
    "end": 723.86,
    "text": "Người nọ dựa vào đâu mà làm vậy, có đủ bản lĩnh để ghi tên mình trên sử sách hay không?"
  },
  {
    "start": 723.86,
    "end": 728.98,
    "text": "Ngũ Vương chi loạn, bắt Vương chi loạn trong lịch sử, rất nhiều trường đại đều đã từng xảy ra."
  },
  {
    "start": 728.98,
    "end": 732.42,
    "text": "Thân ở trong tâm báo, kết cục của bọn họ sẽ ra sao?"
  },
  {
    "start": 732.42,
    "end": 735.12,
    "text": "Thật ra các quan văn cũng không quá sợ hãi."
  },
  {
    "start": 735.12,
    "end": 741.48,
    "text": "Bởi vì cho dù là ai kế vị, đều phải kiên rẻ sử sách ghi chép, kiên rẻ thanh danh của mình trên sử sách."
  },
  {
    "start": 741.48,
    "end": 746.68,
    "text": "Sau này, khi qua đời, sẽ được ghi chép thế nào trên sử sách, được ban thụy hiệu gì?"
  },
  {
    "start": 746.68,
    "end": 751.68,
    "text": "Phải biết rằng, thụy hiệu của Hoàng Đế, cuối cùng phải do các vị Đại Thần quyết định."
  },
  {
    "start": 751.68,
    "end": 757.02,
    "text": "Thông thường, trừ khi là huôn quân, còn không sẽ không ai dám ra tay với các quan văn."
  },
  {
    "start": 757.02,
    "end": 760.52,
    "text": "Trong số đó, người lo lắng nhất chính là thẩm đại nhân."
  },
  {
    "start": 760.52,
    "end": 768.32,
    "text": "Bởi vì chuyện xảy ra trong cung, không ai có thể trốn thoát, không chỉ có các vị Đại Thần đang ở trong cung, mà còn có các hàn lâm đang trực."
  },
  {
    "start": 768.32,
    "end": 774.32,
    "text": "Không khéo là, hàn lâm đang trực hôm nay không phải ai khác, mà chính là đứa con trai cứng đầu của ông ta."
  },
  {
    "start": 774.32,
    "end": 778.72,
    "text": "Suy nghĩ của con cái, Vĩnh Viễn sẽ không đi theo quỹ đạo mà cha mẹ mong muốn."
  },
  {
    "start": 778.72,
    "end": 786.12,
    "text": "Chỉ khi nào đã làm cha mẹ rồi, mới hiểu được, con cái tuy là do mình sinh ra, nuôi nắng, nhưng sau khi lớn lên,"
  },
  {
    "start": 786.12,
    "end": 791.44,
    "text": "Thậm chí có đôi khi nó giống như một con ngựa hoang bất kham, khiến cho cha mẹ bó tay hết cách."
  },
  {
    "start": 791.44,
    "end": 797.96,
    "text": "Thẩm đã nhấn đoán không sai, lúc này trên điện, Hàn Lâm thị giảng thẩm đề đang đối mặt với lưỡi đau sáng loáng của người khác."
  },
  {
    "start": 797.96,
    "end": 801.84,
    "text": "Lưỡi đau sáng loáng, phản chiếu một đôi mắt sáng như sao trời."
  },
  {
    "start": 801.84,
    "end": 807.0,
    "text": "Tên kia mặc giáp trụ, tay cầm đao, dẫn giữ quát, sao lại không phải thật."
  },
  {
    "start": 807.0,
    "end": 810.2,
    "text": "Ngươi nhìn cho kỹ đi, ấn ký nên có đều có đủ."
  },
  {
    "start": 810.2,
    "end": 815.96,
    "text": "Trong tay hắn ta là một cuộn thánh trì bằng lộ vàng, chui trục được làm bằng ngọc, có quy cách cao nhất."
  },
  {
    "start": 815.96,
    "end": 821.32,
    "text": "Đen kia chỉ thiếu điều dí thẳng cuộn thánh trì vào mặt thầm đề, nói, đây là di chiếu của Bể Hạ."
  },
  {
    "start": 821.32,
    "end": 826.92,
    "text": "Lệnh cho Ninh Vương kế thừa Đại Thống, hàn lâm nho nhỏ như người, dám nghi ngờ di chiếu của Bể Hạ."
  },
  {
    "start": 826.92,
    "end": 830.12,
    "text": "Mau viết chiếu thư, để con chiêu cáo thiên hạ."
  },
  {
    "start": 830.12,
    "end": 834.2,
    "text": "Mọi người đều đoán là Tín Vương, Tuyên Vương, hoặc là Cảnh Vương."
  },
  {
    "start": 834.2,
    "end": 836.2,
    "text": "Kết quả lại là Ninh Vương."
  },
  {
    "start": 836.2,
    "end": 842.88,
    "text": "Hoàng đế có rất nhiều con trai, chỉ có tín vương, tuyên vương, cảnh vương là con vợ cả do hoàng hậu sinh ra."
  },
  {
    "start": 842.88,
    "end": 851.0,
    "text": "Nhưng cho dù là con vợ cả, thì Hoàng đế đối xử với các con trai đều như nhau. Hắn ta chỉ yêu bản thân mình, chỉ muốn trưởng sinh bất lão."
  },
  {
    "start": 851.0,
    "end": 859.2,
    "text": "Ninh Vương năm nay đã hơn 50 tuổi, trong số rất nhiều hoàng tử, ngoại trừ đất phong của hắn ta ở gần Kinh Thanh nhất, thì cũng chẳng có gì đặc biệt."
  },
  {
    "start": 859.2,
    "end": 862.84,
    "text": "Mức độ được chú ý còn kém xa ba vị thân vương là con vợ cả."
  },
  {
    "start": 862.84,
    "end": 866.48,
    "text": "Khoan đã, thông tin nhanh chóng được sắp xếp lại trong đầu Thẩm Đề."
  },
  {
    "start": 866.48,
    "end": 872.36,
    "text": "Năm kiến Hoàng thứ 10, Thụy Vương qua đời, người huynh trưởng cuối cùng của Cảnh Vương cũng đã qua đời."
  },
  {
    "start": 872.36,
    "end": 876.28,
    "text": "Bây giờ, Cảnh Vương là người lớn tuổi nhất trong số các Hoàng tử."
  },
  {
    "start": 876.28,
    "end": 882.64,
    "text": "Thẩm Đề nhìn chầm chầm tên kia, nhận lấy cuộn thánh chỉ, mở ra liếc nhìn, đây không phải chữ viết của Bệ Hạ."
  },
  {
    "start": 882.64,
    "end": 887.28,
    "text": "Tên kia tức giận nói, ai quy định di chiếu nhất định phải do Bệ Hạ tự tay viết."
  },
  {
    "start": 887.28,
    "end": 894.28,
    "text": "Thẩm đề nói, vậy đây là chữ viết của ai? Xá nhân nào, hàn lâm nào, hay là thái giám chấp bút nào?"
  },
  {
    "start": 894.28,
    "end": 902.28,
    "text": "Chữ viết của những người có tư cách động bút mực bên cạnh bề hạ, ta đều nhận ra. Chữ viết này không phải của bất kỳ ai trong số bọn họ."
  },
  {
    "start": 902.28,
    "end": 906.28,
    "text": "Đôi mắt hắn ta lệnh lùng như hàn băng, tay cầm đao, tiến lên một bước."
  },
  {
    "start": 906.28,
    "end": 913.72,
    "text": "Di chiếu lập chữ quân, theo tổ chế của Đại Dục, ít nhất phải có hai vị tể tướng chứng kiến, vậy ai là người chứng kiến?"
  },
  {
    "start": 913.72,
    "end": 919.16,
    "text": "Cho dù người có mô phòng giống đến đâu, thì vết dạng trên Ngọc Thạch cũng không thể nào giống y hệt được."
  },
  {
    "start": 919.16,
    "end": 923.64,
    "text": "Ngọc Tỷ được làm rất tinh sảo, ngay cả một góc khuếc cũng được mô phòng theo."
  },
  {
    "start": 923.64,
    "end": 930.2,
    "text": "Chỉ tiếc, ta am hiểu thư họa, giỏi về khắc ấn, cho dù chỉ liếc mắt một cái, ta cũng có thể nhận ra."
  },
  {
    "start": 930.2,
    "end": 935.24,
    "text": "Nói rồi thẩm đề né mạnh cuộn di chiếu kia xuống đất, khiến cho chui chục bằng Ngọc vỡ tan."
  },
  {
    "start": 935.24,
    "end": 940.38,
    "text": "Di chiếu này là giả. Vẻ mặt hắn tan nghiêm nghị, giọng nói lạnh lùng."
  },
  {
    "start": 940.38,
    "end": 946.28,
    "text": "Lòng ngực đã chạm vào mũi đau. Máu đỏ tươi thấm ra, nhụng đỏ quan bào màu xanh lục."
  },
  {
    "start": 946.28,
    "end": 956.28,
    "text": "Tên kia thức giận quá, người muốn chết. Thẩm đề khẽ nhất môi, kinh thường, thậm chí còn dơ tay lên, sờ vào lưỡi đau sắc bén đang kể sát cổ mình, mời."
  },
  {
    "start": 956.28,
    "end": 964.18,
    "text": "Người cùng thẩm đề vào cùng làm việc hôm nay, không phải ai khác, mà chính là Giang Thần Giang Vũ Cực, phú quân của bản thân ẩn oánh, ngô thị."
  },
  {
    "start": 964.18,
    "end": 971.54,
    "text": "Hai người bọn họ cũng bị lôi đến đây, nhưng tên võ phu mặc giáp trụ kia vừa nhìn thấy bọn họ đã hỏi, ai là thẩm đề Thẩm Tế Vân."
  },
  {
    "start": 971.54,
    "end": 978.66,
    "text": "Hắn ta chỉ đích danh thẩm đề, yêu cầu hắn ta viết chiều thư. Lúc ấy Giang Thần đã cảm thấy có chuyện không ổn."
  },
  {
    "start": 978.66,
    "end": 982.66,
    "text": "Với tính tình của Thẩm Tế Vân, quả nhiên, tên kia tức giận."
  },
  {
    "start": 982.66,
    "end": 989.86,
    "text": "Kẻ phía trên kia nói tốt nhất là vị thám hoa lang này, cái câu tốt nhất, ý tư chính là nếu bất thành, người khác cũng có thể."
  },
  {
    "start": 989.86,
    "end": 995.66,
    "text": "Khỉu tay cầm đau của hắn khẽ rụt lại, nâng đau lên, liên chuẩn bị vận lực chém chết kẻ lắm lời này."
  },
  {
    "start": 995.66,
    "end": 1001.26,
    "text": "Giang hàn lâm nhắm mắt lại, dừng tay, một tiếng quát lớn vang lên ngăn cản tên võ phu kia."
  },
  {
    "start": 1001.26,
    "end": 1004.54,
    "text": "Giang thần mở mắt, nhìn về phía người vừa đến."
  },
  {
    "start": 1004.54,
    "end": 1008.9,
    "text": "Thẩm đề cũng nhìn sang. Là một nam tử vận y phục văn sĩ."
  },
  {
    "start": 1008.9,
    "end": 1013.94,
    "text": "Tên võ phu hạ đao xuống, hồ lớn, khâu tiên sinh, hắn không tuần theo."
  },
  {
    "start": 1013.94,
    "end": 1018.38,
    "text": "Khâu tiên sinh bước đến, khách khí chắp tay, vị này là thẩm thám hòa."
  },
  {
    "start": 1018.38,
    "end": 1029.94,
    "text": "Hẳn là môn khách, mưu sĩ gì đó, loại người này, có thể xuất thân bần hàn, nhiều nhất cũng chỉ là tú tài, bởi vì đã là cử nhân thì có thể làm quan, chẳng ai lại đi làm môn khách cho kẻ khác."
  },
  {
    "start": 1029.94,
    "end": 1040.38,
    "text": "Thẩm đề nhập sĩ chưa lâu, chức quan còn thấp. Nhưng Hắn là bậc thanh quý hàn lâm, mầm mống tể tướng, lại còn là thám hoa lang, địa vị trong lòng văn nhân sĩ tử không hề thấp."
  },
  {
    "start": 1040.38,
    "end": 1045.14,
    "text": "Bạch thân hay là mưu sĩ xuất thân tú tài, cân bản không lọt nổi vào mắt xanh của Hán."
  },
  {
    "start": 1045.14,
    "end": 1053.14,
    "text": "Khoa cử mới là chính đạo trong lòng người đọc sách, hạng mưu sĩ bất quá chỉ là kẻ bị đào thải trong khoa cử, là hạng người đầu cơ chính trị mà thôi."
  },
  {
    "start": 1053.14,
    "end": 1055.14,
    "text": "Hết phần 5"
  }
]